polars_partitions/__init__.py
polars_partitions/pl_partitions.py
polars_partitions-0.1.2.dist-info/LICENSE.txt
polars_partitions-0.1.2.dist-info/METADATA
polars_partitions-0.1.2.dist-info/WHEEL
polars_partitions-0.1.2.dist-info/top_level.txt
polars_partitions-0.1.2.dist-info/RECORD
