Metadata-Version: 2.1
Name: polars-partitions
Version: 0.1.2
Summary: Simplified work with partitions based on Polars library
Home-page: https://github.com/dwenlvov/
Author: denis_lvov
Author-email: dwenlvov@gmail.com
Project-URL: Documentation, https://github.com/dwenlvov/polars_partitions
Keywords: polars,partitions,parquet
Classifier: Programming Language :: Python :: 3.11
Classifier: License :: OSI Approved :: MIT License
Requires-Python: >=3.11
License-File: LICENSE.txt
